LICENSE
MANIFEST.in
README.md
package.json
setup.py
musicfox_dash_components/Hello.py
musicfox_dash_components/ToDo.py
musicfox_dash_components/Twash.py
musicfox_dash_components/__init__.py
musicfox_dash_components/_imports_.py
musicfox_dash_components/metadata.json
musicfox_dash_components/musicfox_dash_components.min.js
musicfox_dash_components/musicfox_dash_components.min.js.map
musicfox_dash_components/package-info.json
musicfox_dash_components.egg-info/PKG-INFO
musicfox_dash_components.egg-info/SOURCES.txt
musicfox_dash_components.egg-info/dependency_links.txt
musicfox_dash_components.egg-info/top_level.txt