Metadata-Version: 1.1
Name: musicfox-dash-components
Version: 0.0.70
Summary: Dash components from your favorite mmusic valuation software company [Musicfox](https://musicfox.io)
Home-page: UNKNOWN
Author: Musicfox, Inc. <dev@musicfox.io>
Author-email: UNKNOWN
License: MIT
Platform: UNKNOWN
Classifier: Framework :: Dash
